{
    "Version": "2012-10-17",
    "Statement": [
        {
            "Sid": "ReadOnlyObservabilityAccess",
            "Effect": "Allow",
            "Action": [
                "sts:GetCallerIdentity",
                "logs:DescribeLogGroups",
                "logs:DescribeLogStreams",
                "logs:DescribeQueries",
                "logs:DescribeQueryDefinitions",
                "logs:DescribeMetricFilters",
                "logs:DescribeSubscriptionFilters",
                "logs:DescribeExportTasks",
                "logs:DescribeIndexPolicies",
                "logs:DescribeDestinations",
                "logs:DescribeFieldIndexes",
                "logs:GetLogGroupFields",
                "logs:ListLogAnomalyDetectors",
                "logs:ListLogGroupFieldIndexes",
                "logs:StartQuery",
                "cloudwatch:ListMetrics",
                "cloudwatch:DescribeAlarms",
                "cloudwatch:DescribeAnomalyDetectors",
                "cloudwatch:ListDashboards",
                "cloudwatch:GetDashboard",
                "cloudwatch:ListMetricStreams",
                "ec2:DescribeInstances",
                "ec2:DescribeFlowLogs",
                "lambda:ListFunctions",
                "lambda:GetFunctionConfiguration",
                "xray:GetServiceGraph",
                "xray:GetSamplingRules",
                "xray:GetGroups",
                "xray:GetInsightSummaries",
                "xray:GetTraceSummaries",
                "sns:ListTopics",
                "sns:ListSubscriptions",
                "ecs:ListClusters",
                "ecs:DescribeClusters",
                "ecs:ListTasks",
                "ecs:DescribeTasks",
                "ecs:DescribeTaskDefinition",
                "ecs:ListTaskDefinitions",
                "eks:ListClusters",
                "eks:DescribeCluster",
                "eks:ListAddons",
                "eks:DescribeAddon",
                "synthetics:DescribeCanaries",
                "rum:ListAppMonitors",
                "ssm:DescribeInstanceInformation",
                "application-signals:ListServices",
                "application-signals:ListServiceLevelObjectives",
                "organizations:DescribeOrganization",
                "organizations:DescribeAccount",
                "tag:GetResources",
                "oam:ListLinks",
                "oam:ListSinks",
                "observabilityadmin:ListCentralizationRulesForOrganization",
                "firehose:ListDeliveryStreams",
                "firehose:DescribeDeliveryStream",
                "kinesis:ListStreams"
            ],
            "Resource": "*",
            "Condition": {
                "StringEquals": {
                    "aws:RequestedRegion": "${AssessmentRegion}"
                }
            }
        },
        {
            "Sid": "SSMAgentDetection",
            "Effect": "Allow",
            "Action": [
                "ssm:SendCommand",
                "ssm:GetCommandInvocation"
            ],
            "Resource": "*",
            "Condition": {
                "StringEquals": {
                    "ssm:DocumentName": "AWS-RunShellScript"
                }
            }
        }
    ]
}
